odoo/addons/l10n_ro_account_anaf_sync/README.rst
odoo/addons/l10n_ro_account_anaf_sync/__init__.py
odoo/addons/l10n_ro_account_anaf_sync/__manifest__.py
odoo/addons/l10n_ro_account_anaf_sync/controllers/__init__.py
odoo/addons/l10n_ro_account_anaf_sync/controllers/anaf_oauth.py
odoo/addons/l10n_ro_account_anaf_sync/i18n/l10n_ro_account_anaf_sync.pot
odoo/addons/l10n_ro_account_anaf_sync/i18n/ro.po
odoo/addons/l10n_ro_account_anaf_sync/models/__init__.py
odoo/addons/l10n_ro_account_anaf_sync/models/l10n_ro_account_anaf_sync.py
odoo/addons/l10n_ro_account_anaf_sync/models/l10n_ro_account_anaf_sync_scope.py
odoo/addons/l10n_ro_account_anaf_sync/models/res_company.py
odoo/addons/l10n_ro_account_anaf_sync/readme/CONFIGURE.rst
odoo/addons/l10n_ro_account_anaf_sync/readme/CONTRIBUTORS.rst
odoo/addons/l10n_ro_account_anaf_sync/readme/DESCRIPTION.rst
odoo/addons/l10n_ro_account_anaf_sync/readme/INSTALL.rst
odoo/addons/l10n_ro_account_anaf_sync/readme/Oauth_procedura_inregistrare_aplicatii_portal_ANAF.pdf
odoo/addons/l10n_ro_account_anaf_sync/readme/prezentare apeluri API E-factura.pdf
odoo/addons/l10n_ro_account_anaf_sync/security/account_security.xml
odoo/addons/l10n_ro_account_anaf_sync/security/ir.model.access.csv
odoo/addons/l10n_ro_account_anaf_sync/static/description/icon.png
odoo/addons/l10n_ro_account_anaf_sync/static/description/index.html
odoo/addons/l10n_ro_account_anaf_sync/static/src/json/postman.json
odoo/addons/l10n_ro_account_anaf_sync/tests/__init__.py
odoo/addons/l10n_ro_account_anaf_sync/tests/test_account_anaf_sync.py
odoo/addons/l10n_ro_account_anaf_sync/tests/test_controller.py
odoo/addons/l10n_ro_account_anaf_sync/views/l10n_ro_account_anaf_sync_view.xml
odoo/addons/l10n_ro_account_anaf_sync/views/res_config_view.xml
odoo/addons/l10n_ro_account_anaf_sync/views/template.xml
odoo14_addon_l10n_ro_account_anaf_sync-14.0.1.18.1.dist-info/METADATA
odoo14_addon_l10n_ro_account_anaf_sync-14.0.1.18.1.dist-info/WHEEL
odoo14_addon_l10n_ro_account_anaf_sync-14.0.1.18.1.dist-info/top_level.txt
odoo14_addon_l10n_ro_account_anaf_sync-14.0.1.18.1.dist-info/RECORD
